[
    {
        "name": "Atlantic Cod",
        "depthRange": {
            "min": 50,
            "max": 200
        },
        "rarity": "common",
        "valueRange": {
            "min": 10,
            "max": 20
        },
        "weightRange": {
            "min": 1,
            "max": 50
        },
        "lengthRange": {
            "min": 70,
            "max": 200
        },
        "lureLevel": 1
    },
    {
        "name": "Blue Marlin",
        "depthRange": {
            "min": 100,
            "max": 500
        },
        "rarity": "rare",
        "valueRange": {
            "min": 50,
            "max": 100
        },
        "weightRange": {
            "min": 10,
            "max": 120
        },
        "lengthRange": {
            "min": 200,
            "max": 500
        },
        "lureLevel": 3
    }
]